CHANGES.txt
MANIFEST.in
README.txt
setup.py
src/typeinfo.py
src/typeinfo.egg-info/PKG-INFO
src/typeinfo.egg-info/SOURCES.txt
src/typeinfo.egg-info/dependency_links.txt
src/typeinfo.egg-info/not-zip-safe
src/typeinfo.egg-info/top_level.txt