Metadata-Version: 1.0
Name: typeinfo
Version: 0.1
Summary: A library to add optional type information to python objects.
Home-page: UNKNOWN
Author: TypeInfo Developers
Author-email: b.leskes@gmail.com
License: apache
Platform: UNKNOWN
